{
  "last_run": "2026-07-23T14:40:44.679325+05:30",
  "stocks": {
    "M&M": {
      "symbol": "M&M.NS",
      "sector": "Automobile",
      "position": "above",
      "last_cross": "BREAKDOWN",
      "cross_time": "2026-07-23T14:40:37.942606+05:30",
      "alerted": false,
      "close": 3219.9,
      "ema20": 3213.76,
      "initialized": true
    },
    "Hero Motocorp": {
      "symbol": "HEROMOTOCO.NS",
      "sector": "Automobile",
      "position": "above",
      "last_cross": "BREAKDOWN",
      "cross_time": "2026-07-23T14:40:38.100066+05:30",
      "alerted": false,
      "close": 5168.9,
      "ema20": 5114.36,
      "initialized": true
    },
    "KPIT Technology": {
      "symbol": "KPITTECH.NS",
      "sector": "IT",
      "position": "below",
      "last_cross": "BREAKDOWN",
      "cross_time": "2026-07-23T14:40:38.235959+05:30",
      "alerted": false,
      "close": 550.6,
      "ema20": 553.6,
      "initialized": true
    },
    "Mphasis": {
      "symbol": "MPHASIS.NS",
      "sector": "IT",
      "position": "below",
      "last_cross": "BREAKOUT",
      "cross_time": "2026-07-23T14:40:38.871440+05:30",
      "alerted": false,
      "close": 2236.0,
      "ema20": 2266.87,
      "initialized": true
    },
    "Maruti": {
      "symbol": "MARUTI.NS",
      "sector": "Automobile",
      "position": "below",
      "last_cross": "BREAKDOWN",
      "cross_time": "2026-07-23T14:40:39.108257+05:30",
      "alerted": true,
      "close": 13399.0,
      "ema20": 13493.28,
      "initialized": true
    },
    "DLF": {
      "symbol": "DLF.NS",
      "sector": "Realty",
      "position": "below",
      "last_cross": null,
      "cross_time": null,
      "alerted": false,
      "close": 641.65,
      "ema20": 650.6,
      "initialized": true
    },
    "Dixon": {
      "symbol": "DIXON.NS",
      "sector": "Electronics",
      "position": "below",
      "last_cross": "BREAKDOWN",
      "cross_time": "2026-07-23T14:40:39.381914+05:30",
      "alerted": true,
      "close": 13806.0,
      "ema20": 13916.52,
      "initialized": true
    },
    "SHRIRAM Finance": {
      "symbol": "SHRIRAMFIN.NS",
      "sector": "Finance",
      "position": "below",
      "last_cross": "BREAKDOWN",
      "cross_time": "2026-07-23T14:40:39.528301+05:30",
      "alerted": false,
      "close": 1027.8,
      "ema20": 1044.82,
      "initialized": true
    },
    "Indigo": {
      "symbol": "INDIGO.NS",
      "sector": "Aviation",
      "position": "below",
      "last_cross": "BREAKDOWN",
      "cross_time": "2026-07-23T14:40:39.654088+05:30",
      "alerted": false,
      "close": 5000.0,
      "ema20": 5090.76,
      "initialized": true
    },
    "Eicher Motors": {
      "symbol": "EICHERMOT.NS",
      "sector": "Automobile",
      "position": "above",
      "last_cross": "BREAKDOWN",
      "cross_time": "2026-07-23T14:40:39.811346+05:30",
      "alerted": false,
      "close": 7706.5,
      "ema20": 7685.99,
      "initialized": true
    },
    "Bajaj Auto": {
      "symbol": "BAJAJ-AUTO.NS",
      "sector": "Automobile",
      "position": "above",
      "last_cross": null,
      "cross_time": null,
      "alerted": false,
      "close": 11253.5,
      "ema20": 11109.53,
      "initialized": true
    },
    "VEDL": {
      "symbol": "VEDL.NS",
      "sector": "Metals",
      "position": "above",
      "last_cross": "BREAKDOWN",
      "cross_time": "2026-07-23T14:40:40.195272+05:30",
      "alerted": false,
      "close": 264.5,
      "ema20": 264.45,
      "initialized": true
    },
    "HAL": {
      "symbol": "HAL.NS",
      "sector": "Defence",
      "position": "above",
      "last_cross": "BREAKOUT",
      "cross_time": "2026-07-23T14:40:40.322666+05:30",
      "alerted": true,
      "close": 4568.8,
      "ema20": 4567.65,
      "initialized": true
    },
    "JSW Steel": {
      "symbol": "JSWSTEEL.NS",
      "sector": "Metals",
      "position": "below",
      "last_cross": "BREAKDOWN",
      "cross_time": "2026-07-23T14:40:40.499586+05:30",
      "alerted": true,
      "close": 1240.4,
      "ema20": 1255.96,
      "initialized": true
    },
    "LT": {
      "symbol": "LT.NS",
      "sector": "Infrastructure",
      "position": "below",
      "last_cross": "BREAKDOWN",
      "cross_time": "2026-07-23T14:40:40.647316+05:30",
      "alerted": false,
      "close": 3787.9,
      "ema20": 3808.83,
      "initialized": true
    },
    "SBIN": {
      "symbol": "SBIN.NS",
      "sector": "Banking",
      "position": "below",
      "last_cross": null,
      "cross_time": null,
      "alerted": false,
      "close": 1012.8,
      "ema20": 1019.72,
      "initialized": true
    },
    "Persistent Systems": {
      "symbol": "PERSISTENT.NS",
      "sector": "IT",
      "position": "below",
      "last_cross": null,
      "cross_time": null,
      "alerted": false,
      "close": 5010.2,
      "ema20": 5060.56,
      "initialized": true
    },
    "Tata Steel": {
      "symbol": "TATASTEEL.NS",
      "sector": "Metals",
      "position": "below",
      "last_cross": "BREAKOUT",
      "cross_time": "2026-07-23T14:40:41.117466+05:30",
      "alerted": false,
      "close": 183.98,
      "ema20": 185.09,
      "initialized": true
    },
    "BHEL": {
      "symbol": "BHEL.NS",
      "sector": "Capital Goods",
      "position": "below",
      "last_cross": "BREAKDOWN",
      "cross_time": "2026-07-23T14:40:41.265489+05:30",
      "alerted": false,
      "close": 409.35,
      "ema20": 412.02,
      "initialized": true
    },
    "ABB": {
      "symbol": "ABB.NS",
      "sector": "Capital Goods",
      "position": "below",
      "last_cross": "BREAKDOWN",
      "cross_time": "2026-07-23T14:40:41.422406+05:30",
      "alerted": false,
      "close": 7529.0,
      "ema20": 7567.13,
      "initialized": true
    },
    "Siemens": {
      "symbol": "SIEMENS.NS",
      "sector": "Capital Goods",
      "position": "above",
      "last_cross": "BREAKOUT",
      "cross_time": "2026-07-23T14:40:41.620897+05:30",
      "alerted": true,
      "close": 3672.8,
      "ema20": 3671.01,
      "initialized": true
    },
    "NTPC": {
      "symbol": "NTPC.NS",
      "sector": "Power",
      "position": "below",
      "last_cross": "BREAKDOWN",
      "cross_time": "2026-07-23T14:40:41.757944+05:30",
      "alerted": false,
      "close": 347.6,
      "ema20": 348.36,
      "initialized": true
    },
    "National Aluminium": {
      "symbol": "NATIONALUM.NS",
      "sector": "Metals",
      "position": "above",
      "last_cross": "BREAKOUT",
      "cross_time": "2026-07-23T14:40:41.934553+05:30",
      "alerted": true,
      "close": 346.15,
      "ema20": 345.45,
      "initialized": true
    },
    "Kaynes": {
      "symbol": "KAYNES.NS",
      "sector": "Electronics",
      "position": "below",
      "last_cross": "BREAKOUT",
      "cross_time": "2026-07-23T14:40:42.051757+05:30",
      "alerted": false,
      "close": 3240.0,
      "ema20": 3265.54,
      "initialized": true
    },
    "MCX": {
      "symbol": "MCX.NS",
      "sector": "Finance",
      "position": "below",
      "last_cross": "BREAKOUT",
      "cross_time": "2026-07-23T14:40:42.188084+05:30",
      "alerted": false,
      "close": 2744.6,
      "ema20": 2760.68,
      "initialized": true
    },
    "BSE": {
      "symbol": "BSE.NS",
      "sector": "Finance",
      "position": "below",
      "last_cross": "BREAKOUT",
      "cross_time": "2026-07-23T14:40:42.314572+05:30",
      "alerted": false,
      "close": 3586.9,
      "ema20": 3611.95,
      "initialized": true
    },
    "Trent": {
      "symbol": "TRENT.NS",
      "sector": "Retail",
      "position": "below",
      "last_cross": "BREAKOUT",
      "cross_time": "2026-07-23T14:40:42.488382+05:30",
      "alerted": false,
      "close": 2871.1,
      "ema20": 2888.92,
      "initialized": true
    },
    "Asian Paints": {
      "symbol": "ASIANPAINT.NS",
      "sector": "Consumer",
      "position": "below",
      "last_cross": "BREAKOUT",
      "cross_time": "2026-07-23T14:40:42.645636+05:30",
      "alerted": false,
      "close": 2666.0,
      "ema20": 2676.72,
      "initialized": true
    },
    "OFSS": {
      "symbol": "OFSS.NS",
      "sector": "IT",
      "position": "below",
      "last_cross": "BREAKDOWN",
      "cross_time": "2026-07-23T14:40:42.791939+05:30",
      "alerted": false,
      "close": 10775.0,
      "ema20": 10855.76,
      "initialized": true
    },
    "Hindalco": {
      "symbol": "HINDALCO.NS",
      "sector": "Metals",
      "position": "above",
      "last_cross": "BREAKOUT",
      "cross_time": "2026-07-23T14:40:42.969077+05:30",
      "alerted": true,
      "close": 952.8,
      "ema20": 952.69,
      "initialized": true
    },
    "Cummins India": {
      "symbol": "CUMMINSIND.NS",
      "sector": "Capital Goods",
      "position": "below",
      "last_cross": "BREAKOUT",
      "cross_time": "2026-07-23T14:40:43.126855+05:30",
      "alerted": false,
      "close": 5592.0,
      "ema20": 5594.73,
      "initialized": true
    },
    "TCS": {
      "symbol": "TCS.NS",
      "sector": "IT",
      "position": "above",
      "last_cross": "BREAKOUT",
      "cross_time": "2026-07-23T14:40:43.273102+05:30",
      "alerted": true,
      "close": 2243.0,
      "ema20": 2224.45,
      "initialized": true
    },
    "Infosys": {
      "symbol": "INFY.NS",
      "sector": "IT",
      "position": "below",
      "last_cross": "BREAKDOWN",
      "cross_time": "2026-07-23T14:40:43.540263+05:30",
      "alerted": true,
      "close": 1047.6,
      "ema20": 1050.04,
      "initialized": true
    },
    "Tata Elxsi": {
      "symbol": "TATAELXSI.NS",
      "sector": "IT",
      "position": "below",
      "last_cross": "BREAKDOWN",
      "cross_time": "2026-07-23T14:40:43.687960+05:30",
      "alerted": false,
      "close": 3388.2,
      "ema20": 3405.31,
      "initialized": true
    },
    "Bajaj Finance": {
      "symbol": "BAJFINANCE.NS",
      "sector": "Finance",
      "position": "below",
      "last_cross": "BREAKOUT",
      "cross_time": "2026-07-23T14:40:43.824813+05:30",
      "alerted": false,
      "close": 1040.5,
      "ema20": 1052.49,
      "initialized": true
    },
    "Polycab": {
      "symbol": "POLYCAB.NS",
      "sector": "Electronics",
      "position": "below",
      "last_cross": "BREAKOUT",
      "cross_time": "2026-07-23T14:40:43.963035+05:30",
      "alerted": false,
      "close": 8926.0,
      "ema20": 9001.03,
      "initialized": true
    },
    "ICICI Bank": {
      "symbol": "ICICIBANK.NS",
      "sector": "Banking",
      "position": "below",
      "last_cross": null,
      "cross_time": null,
      "alerted": false,
      "close": 1430.8,
      "ema20": 1438.24,
      "initialized": true
    },
    "Lupin": {
      "symbol": "LUPIN.NS",
      "sector": "Pharma",
      "position": "below",
      "last_cross": "BREAKOUT",
      "cross_time": "2026-07-23T14:40:44.278833+05:30",
      "alerted": false,
      "close": 2392.1,
      "ema20": 2411.74,
      "initialized": true
    },
    "Laurus Labs": {
      "symbol": "LAURUSLABS.NS",
      "sector": "Pharma",
      "position": "below",
      "last_cross": "BREAKDOWN",
      "cross_time": "2026-07-23T14:40:44.415437+05:30",
      "alerted": true,
      "close": 1570.2,
      "ema20": 1574.29,
      "initialized": true
    },
    "NIFTY 50": {
      "symbol": "^NSEI",
      "sector": "Index",
      "position": "below",
      "last_cross": "BREAKOUT",
      "cross_time": "2026-07-23T14:40:44.533119+05:30",
      "alerted": false,
      "close": 23850.2,
      "ema20": 23940.52,
      "initialized": true
    }
  }
}